[
    {
        "id": 102,
        "title": "面積の差は？",
        "desc": "4年生: 面積",
        "q": [
            {
                "qId": 1,
                "q": "[問題]<br/>一辺7cmと一辺5cmの正方形があります。<br/>この2つの正方形を重ねて, それぞれ重なっていないところの面積（アとイ）の差は, 何㎠になるでしょうか。<br/>（ウは, 重なっているところの面積）<br/><img src='../img/102.png' style='width:50%; margin:auto;'></img>",
                "qs": [
                    {
                        "qId": 1,
                        "q": "",
                        "a": [
                            "模範解答1",
                            "模範解答2"
                        ]
                    }
                ]
            }
        ]
    }
]