[{"id":100,"student":3,"data":[{"x":104,"y":93,"status":"start","mode":"pen","time":1656383515842},{"x":114,"y":94,"status":"move"},{"x":128,"y":94,"status":"move"},{"x":154,"y":94,"status":"move"},{"x":181,"y":93,"status":"move"},{"x":200,"y":91,"status":"move"},{"x":206,"y":90,"status":"move"},{"x":206,"y":90,"status":"end"},{"x":151,"y":79,"status":"start","mode":"pen","time":1656383516108},{"x":149,"y":85,"status":"move"},{"x":147,"y":104,"status":"move"},{"x":146,"y":133,"status":"move"},{"x":145,"y":169,"status":"move"},{"x":144,"y":200,"status":"move"},{"x":143,"y":216,"status":"move"},{"x":143,"y":222,"status":"move"},{"x":143,"y":222,"status":"end"},{"x":167,"y":173,"status":"start","mode":"pen","time":1656383516408},{"x":161,"y":178,"status":"move"},{"x":145,"y":189,"status":"move"},{"x":127,"y":199,"status":"move"},{"x":111,"y":204,"status":"move"},{"x":99,"y":206,"status":"move"},{"x":94,"y":205,"status":"move"},{"x":92,"y":204,"status":"move"},{"x":91,"y":199,"status":"move"},{"x":91,"y":190,"status":"move"},{"x":96,"y":178,"status":"move"},{"x":104,"y":168,"status":"move"},{"x":116,"y":160,"status":"move"},{"x":129,"y":157,"status":"move"},{"x":145,"y":159,"status":"move"},{"x":161,"y":166,"status":"move"},{"x":176,"y":176,"status":"move"},{"x":186,"y":187,"status":"move"},{"x":191,"y":195,"status":"move"},{"x":192,"y":198,"status":"move"},{"x":192,"y":201,"status":"move"},{"x":191,"y":203,"status":"move"},{"x":190,"y":204,"status":"move"},{"x":189,"y":205,"status":"move"},{"x":189,"y":205,"status":"end"},{"x":241,"y":177,"status":"start","mode":"pen","time":1656383516925},{"x":241,"y":178,"status":"move"},{"x":241,"y":181,"status":"move"},{"x":240,"y":188,"status":"move"},{"x":238,"y":197,"status":"move"},{"x":237,"y":203,"status":"move"},{"x":237,"y":207,"status":"move"},{"x":237,"y":209,"status":"move"},{"x":237,"y":209,"status":"move"},{"x":237,"y":209,"status":"end"},{"x":361,"y":142,"status":"start","mode":"pen","time":1656383517159},{"x":361,"y":142,"status":"move"},{"x":360,"y":144,"status":"move"},{"x":359,"y":149,"status":"move"},{"x":358,"y":157,"status":"move"},{"x":358,"y":165,"status":"move"},{"x":358,"y":171,"status":"move"},{"x":359,"y":173,"status":"move"},{"x":359,"y":174,"status":"move"},{"x":359,"y":174,"status":"end"},{"x":391,"y":90,"status":"start","mode":"pen","time":1656383517458},{"x":392,"y":91,"status":"move"},{"x":394,"y":92,"status":"move"},{"x":398,"y":95,"status":"move"},{"x":402,"y":99,"status":"move"},{"x":404,"y":105,"status":"move"},{"x":404,"y":113,"status":"move"},{"x":404,"y":113,"status":"end"},{"x":353,"y":180,"status":"start","mode":"pen","time":1656383517642},{"x":354,"y":179,"status":"move"},{"x":356,"y":178,"status":"move"},{"x":368,"y":173,"status":"move"},{"x":396,"y":164,"status":"move"},{"x":435,"y":156,"status":"move"},{"x":462,"y":152,"status":"move"},{"x":470,"y":153,"status":"move"},{"x":474,"y":156,"status":"move"},{"x":476,"y":164,"status":"move"},{"x":476,"y":175,"status":"move"},{"x":472,"y":187,"status":"move"},{"x":463,"y":197,"status":"move"},{"x":453,"y":204,"status":"move"},{"x":446,"y":207,"status":"move"},{"x":443,"y":207,"status":"move"},{"x":443,"y":207,"status":"end"}]},{"id":100,"student":3,"data":[]},{"id":100,"student":3,"data":[]},{"id":100,"student":3,"data":[]}]